README.md
setup.py
Excelacceslib/__init__.py
Excelacceslib/excel_matrix_manage.py
Excelacceslib.egg-info/PKG-INFO
Excelacceslib.egg-info/SOURCES.txt
Excelacceslib.egg-info/dependency_links.txt
Excelacceslib.egg-info/not-zip-safe
Excelacceslib.egg-info/requires.txt
Excelacceslib.egg-info/top_level.txt