Metadata-Version: 2.1
Name: Excelacceslib
Version: 0.0.4
Summary: This lib controls Excel files for ProbeCard project
Home-page: UNKNOWN
License: CC0 1.0 Universal
Platform: UNKNOWN
Classifier: Development Status :: 4 - Beta
Classifier: Programming Language :: Python :: 3
Requires-Python: >=3
